Tmc_con_tc_hm.py
Tmc_con_tc_hm-1.0.dist-info/METADATA
Tmc_con_tc_hm-1.0.dist-info/WHEEL
Tmc_con_tc_hm-1.0.dist-info/top_level.txt
Tmc_con_tc_hm-1.0.dist-info/RECORD
