Metadata-Version: 2.1
Name: Tmc-con-tc-hm
Version: 1.0
Summary: time conversion of seconds to minutes,hours and days
Home-page: https://github.com/HemalathaB28/Tmc_con_tc_hm
Author: HEMALATHA B
Author-email: <bhema2802@gmail.com>
License: UNKNOWN
Platform: UNKNOWN
Classifier: Programming Language :: Python :: 3.5
Classifier: Programming Language :: Python :: 3.6
Classifier: Programming Language :: Python :: 3.7
Classifier: Programming Language :: Python :: 3.8
Classifier: Operating System :: OS Independent
